eziql/__init__.py
eziql/core.py
eziql-0.1.2.dist-info/METADATA
eziql-0.1.2.dist-info/WHEEL
eziql-0.1.2.dist-info/top_level.txt
eziql-0.1.2.dist-info/RECORD
