Metadata-Version: 2.1
Name: eziql
Version: 0.1.2
Summary: Generate SQL queries from natural language using Groq's LLaMA model.
Home-page: https://github.com/aman-prajapat/eziql
Author: Aman Prajapat
Author-email: prajapataman007@gmail.com
License: MIT
Classifier: Programming Language :: Python :: 3
Classifier: License :: OSI Approved :: MIT License
Classifier: Operating System :: OS Independent
Requires-Python: >=3.7
Requires-Dist: groq
Requires-Dist: python-dotenv
